urlfile/__init__.py
urlfile-1.0.1.dist-info/LICENSE
urlfile-1.0.1.dist-info/METADATA
urlfile-1.0.1.dist-info/WHEEL
urlfile-1.0.1.dist-info/top_level.txt
urlfile-1.0.1.dist-info/RECORD
