Metadata-Version: 2.1
Name: urlfile
Version: 1.0.1
Summary: Lazily reading a file from a url. Allows random access via http range requests.
Home-page: https://github.com/sjmillius/urlfile
License: Apache License 2.0
Project-URL: Homepage, https://github.com/sjmillius/urlfile
Project-URL: Bug Tracker, https://github.com/sjmillius/urlfile/issues
Keywords: url,range,lazy,file
License-File: LICENSE
Requires-Dist: cachetools
Requires-Dist: requests
Requires-Dist: rich
